orm_alchemy/__init__.py
orm_alchemy/alchemy.py
orm_alchemy/decorator.py
orm_alchemy-0.1.14.dist-info/LICENSE
orm_alchemy-0.1.14.dist-info/WHEEL
orm_alchemy-0.1.14.dist-info/METADATA
orm_alchemy-0.1.14.dist-info/RECORD
